ai4s/bio/crisprprimer/__init__.py
ai4s-0.1.0.dist-info/METADATA
ai4s-0.1.0.dist-info/WHEEL
ai4s-0.1.0.dist-info/RECORD
