Metadata-Version: 2.3
Name: ai4s
Version: 0.1.0
Summary: AI for Science
Author-email: Tang Ziya <tcztzy@gmail.Com>
Requires-Python: >=3.8
